weep/__init__.py
weep-0.0.1.dist-info/LICENSE
weep-0.0.1.dist-info/METADATA
weep-0.0.1.dist-info/WHEEL
weep-0.0.1.dist-info/top_level.txt
weep-0.0.1.dist-info/RECORD
