Metadata-Version: 2.1
Name: weep
Version: 0.0.1
Summary: Python library for Weep, the ConsoleMe CLI
Home-page: https://github.com/Netflix/weep-python
Author: Patrick Sanders
Author-email: consoleme-maintainers@netflix.com
License: UNKNOWN
Project-URL: Bug Tracker, https://github.com/Netflix/weep-python/issues
Platform: UNKNOWN
Classifier: Intended Audience :: Developers
Classifier: Intended Audience :: Information Technology
Classifier: Programming Language :: Python :: 3
Classifier: License :: OSI Approved :: Apache Software License
Classifier: Operating System :: OS Independent
Classifier: Topic :: Security
Classifier: Topic :: Software Development :: Libraries :: Python Modules
Classifier: Topic :: Utilities
Requires-Python: >=3.6
License-File: LICENSE
